dbbasic_admin/__init__.py
dbbasic_admin/admin.py
dbbasic_admin/discover.py
dbbasic_admin/api/__init__.py
dbbasic_admin/api/database.py
dbbasic_admin/api/nav.py
dbbasic_admin-0.1.1.dist-info/METADATA
dbbasic_admin-0.1.1.dist-info/WHEEL
dbbasic_admin-0.1.1.dist-info/top_level.txt
dbbasic_admin-0.1.1.dist-info/RECORD
