Metadata-Version: 2.4
Name: dbbasic-admin
Version: 0.1.1
Summary: Auto-discovery admin interface for dbbasic modules
Author-email: DBBASIC Team <hello@dbbasic.com>
License: MIT
Project-URL: Homepage, https://dbbasic.com
Project-URL: Documentation, https://dbbasic.com/admin-spec
Project-URL: Repository, https://github.com/askrobots/dbbasic-admin
Keywords: admin,dbbasic,crud,auto-discovery
Classifier: Development Status :: 3 - Alpha
Classifier: Intended Audience :: Developers
Classifier: License :: OSI Approved :: MIT License
Classifier: Programming Language :: Python :: 3
Classifier: Programming Language :: Python :: 3.9
Classifier: Programming Language :: Python :: 3.10
Classifier: Programming Language :: Python :: 3.11
Classifier: Programming Language :: Python :: 3.12
Requires-Python: >=3.9
Requires-Dist: jinja2>=3.1.0
Requires-Dist: dbbasic-web>=0.1.8
Provides-Extra: dev
Requires-Dist: pytest>=7.0; extra == "dev"
Requires-Dist: pytest-asyncio>=0.21.0; extra == "dev"
